{"head_email": "walter@example.com",
"sales_1of2": "",
"sales_1of5": "",
"sales_2of2": "",
"sales_2of5": "",
"sales_3of5": "",
"sales_4of5": "",
"sales_5of5": "",
"product_age": "4",
"roi_details": "1",
"website_url": "example.com",
"applying_for": "organisation",
"company_name": "1231",
"exports_1of2": "0",
"exports_1of5": "",
"exports_2of2": "0",
"exports_2of5": "",
"exports_3of5": "",
"exports_4of5": "",
"exports_5of5": "",
"grant_details": "",
"grant_support": "no",
"org_telephone": "1",
"drops_in_sales": "",
"employees_1of2": "10",
"employees_1of5": "",
"employees_2of2": "20",
"employees_2of5": "",
"employees_3of5": "",
"employees_4of5": "",
"employees_5of5": "",
"head_job_title": "Chief",
"sic_code": "0111",
"net_profit_1of2": "100000",
"net_profit_1of5": "",
"net_profit_2of2": "100000",
"net_profit_2of5": "",
"net_profit_3of5": "",
"net_profit_4of5": "",
"net_profit_5of5": "",
"units_sold_1of2": "",
"units_sold_1of5": "",
"units_sold_2of2": "",
"units_sold_2of5": "",
"units_sold_3of5": "",
"units_sold_4of5": "",
"units_sold_5of5": "",
"entry_relates_to": "entire_business",
"other_awards_won": "no",
"costs_change_desc": "",
"drops_in_turnover": "yes",
"impact_on_society": "1",
"other_awards_desc": "",
"entry_confirmation": "on",
"shortlisted_case_confirmation": "on",
"due_diligence": "on",
"parent_group_entry": "yes",
"partners_relations": "1",
"principal_business": "yes",
"applied_for_queen_awards": "no",
"sales_exports_1of2": "",
"sales_exports_1of5": "",
"sales_exports_2of2": "",
"sales_exports_2of5": "",
"sales_exports_3of5": "",
"sales_exports_4of5": "",
"sales_exports_5of5": "",
"sector_leader_desc": "1",
"customers_relations": "1",
"employees_relations": "1",
"investments_details": "1",
"licensing_agreement": "1",
"application_relate_to": "[\"{\\\"type\\\":\\\"product\\\"}\"]",
"part_of_joint_entry": "no",
"organisation_type": "ltd",
"registration_number": "N/A",
"vat_registration_number": "N/A",
"social_contribution": "1",
"started_trading_day": "01",
"total_turnover_1of2": "100000",
"total_turnover_1of5": "",
"total_turnover_2of2": "1000001",
"total_turnover_2of5": "",
"total_turnover_3of5": "",
"total_turnover_4of5": "",
"total_turnover_5of5": "",
"another_org_licensed": "no",
"sales_royalties_1of2": "",
"sales_royalties_1of5": "",
"sales_royalties_2of2": "",
"sales_royalties_2of5": "",
"sales_royalties_3of5": "",
"sales_royalties_4of5": "",
"sales_royalties_5of5": "",
"started_trading_year": "1999",
"you_released_product": "no",
"development_desc_long": "1",
"economic_contribution": "1",
"impact_on_environment": "1",
"product_estimates_use": "",
"started_trading_month": "10",
"total_net_assets_1of2": "100000",
"total_net_assets_1of5": "",
"total_net_assets_2of2": "100000",
"total_net_assets_2of5": "",
"total_net_assets_3of5": "",
"total_net_assets_4of5": "",
"total_net_assets_5of5": "",
"development_desc_short": "1",
"head_of_bussines_title": "prof",
"parent_company_country": "GB",
"previous_business_name": "",
"organization_address_city": "1",
"avg_unit_cost_self_1of2": "",
"avg_unit_cost_self_1of5": "",
"avg_unit_cost_self_2of2": "",
"avg_unit_cost_self_2of5": "",
"avg_unit_cost_self_3of5": "",
"avg_unit_cost_self_4of5": "",
"avg_unit_cost_self_5of5": "",
"confirmation_of_consent": "on",
"development_performance": "1",
"development_performance_years":"3 to 5",
"financial_year_date_day": "1",
"leadership_contribution": "1",
"pareent_group_excluding": "yes",
"impact_on_society": "test",
"impact_on_environment": "test",
"partners_relations": "test",
"employees_relations": "test",
"customers_relations": "test",
"declaration_of_corporate_responsibility": "1",
"head_of_business_honours": "",
"invoicing_unit_relations": "",
"organization_address_region": "East",
"organization_address_street": "1",
"ultimate_control_company": "test",
"financial_year_date_month": "1",
"part_of_joint_entry_names": "",
"previous_business_ref_num": "",
"organization_address_county": "Buckinghamshire",
"covid_impact_details": "test",
"product_estimated_figures": "no",
"environmental_contribution": "1",
"head_of_business_last_name": "White",
"organization_address_building": "1",
"organization_address_postcode": "1",
"applied_for_queen_awards_details": "[\"{\\\"category\\\":\\\"\\\",\\\"year\\\":\\\"\\\",\\\"outcome\\\":\\\"\\\"}\"]",
"financial_year_date_changed": "no",
"head_of_business_first_name": "Walter",
"head_of_bussines_title_other": "",
"development_additional_comments": "1",
"development_excluded_explanation": "1",
"ultimate_control_company_country": "GB",
"financial_year_changed_dates_1of2day": "",
"financial_year_changed_dates_1of5day": "",
"financial_year_changed_dates_2of5day": "",
"financial_year_changed_dates_3of5day": "",
"financial_year_changed_dates_4of5day": "",
"financial_year_changed_dates_1of2month": "",
"financial_year_changed_dates_1of5month": "",
"financial_year_changed_dates_2of5month": "",
"financial_year_changed_dates_3of5month": "",
"financial_year_changed_dates_4of5month": "",
"financial_year_date_changed_explaination": "",
"external_contribute_to_sustainable_product": "no",
"name_of_external_organization_or_individual": "Davos",
"agree_being_contacted_by_department_of_business": "on",
"agree_being_contacted_about_issues_not_related_to_application": "on",
"company_estimated_figures": "yes",
"why_external_organisations_contributed_your_nomination": "test",
"parent_or_a_holding_company": "yes",
"parent_company": "test",
"parent_ultimate_control": "yes",
"development_management_approach_briefly": "test",
"development_was_launched_since_day": "01",
"development_was_launched_since_month": "09",
"development_was_launched_since_year": "2011",
"press_contact_details_title": "Mr",
"press_contact_details_first_name": "John",
"press_contact_details_last_name": "Doe",
"press_contact_details_telephone": "+4411111111111",
"press_contact_details_email": "test@example.com",
"company_estimates_use": "1",
"describe_your_interventions_using_un": "test",
"one_line_description_of_interventions": "test",
"briefly_describe_your_core_business": "test",
"impact_of_your_sustainable_development": "test",
"describe_the_driving_force_of_your_organisation": "test",
"culture_and_values_regarding_sustainability": "test",
"explain_why_your_organisation_is_financially_viable": "test",
"how_did_you_hear_about_award": [{"type":"other"}, {"type": "another_website"}],
"covid_19_impact": "test",
"governance": "test",
"briefly_describe_your_interventions": "test",
"describe_previous_situation_before_sustainability": "test",
"why_these_particular_interventions": "test",
"how_have_you_embedded_sustainability_objectives": "test",
"explain_how_the_business_operates_sustainably": "test",
"how_sustainability_interventions_benefit_business_strategy": "test",
"explain_your_strategy_in_developing_sustainably": "test",
"who_is_responsible_for_day_to_day_management": "test",
"describe_the_senior_decision_makers_commitment_to_sustainability": "test",
"how_does_your_organisation_inspire_others": "test",
"how_do_you_collaborate_with_partners": "test",
"describe_your_organisation_diversity": "test",
"describe_how_employee_relations_improved_their_motivation": "test",
"how_do_you_increase_positive_perception_of_sustainability": "test",
"how_do_you_communicate_the_impact_of_sustainability": "test",
"what_are_your_long_term_plans_for_sustainability": "test",
"aims_of_the_interventions": "test",
"proportion_of_interventions_compared_to_organisation_size": "test",
"evidence_of_exemplary_interventions": "test",
"how_do_you_measure_the_success_of_interventions": "test",
"what_qualitive_measures_were_used_to_measure_success": "test",
"how_does_the_scale_of_intervention_compare_to_others": "test",
"what_longer_term_outcomes_do_you_expect": "test",
"which_accreditations_have_been_achieved": "test",
"brand_name": "test",
"organisation_worthiness": "yes",
"enquiries_consent": "on",
"commercial_performance": "on",
"external_contributors": "test",
"financial_adjustments_explanation": "test",
"agree_to_provide_actual_figures": "on"}
